Workbook

Sheet Sheet1
B1: Company Report | O1: Report's Date: | P1: =+TODAY() -> 46076
B2: Overall | J2: Sentiment
D4: Company:
D5: Country: | K5: Nr. Analysts (atm):
D6: Sector:
D7: Industry: | J7: Period | K7: Strong Buy | L7: Buy | M7: Hold | N7: Sell | O7: Strong Sell
D8: Ticker: | J8: Now
D9: Employees: | J9: 1 Month ago
D10: Market Cap.: | J10: 2 Months ago
D11: Stock Price: | F11: (currency) | J11: 3 Months ago
D12: 52week range: | P12: Rating
D13: Dividend yield: | J13: Overall Recommendation: | P13: =+IF(OR(L13="",L13="none"),"",VLOOKUP(L13,Sheet2!$A$1:$B$6,2,FALSE))
P14: Rating
B15: Company's description | J15: Beta: | L15: -----> | M15: =IF(K15="","",IF(K15<0.8,"Low volatility",IF(K15<=1.2,"Normal volatility","High volatility"))) | P15: =+IF(M15="","",VLOOKUP(M15,Sheet2!$A$8:$B$11,2,FALSE))
J16: Notes:
J17: Earnings Dates
J18: date1
J19: date2
J20: date3
B22: Stock performance | F22: Category: | G22: (Growth/Dividends) | J22: Current Profit Margin:
J23: Current EBITDA:
J27: Risks
J28: Audit:
J29: Board:
J30: Compensation:
J31: Shareholder rights:
P32: Rating
J33: Overall: | P33: =+IF(L33="","",VLOOKUP(L33,Sheet2!$A$13:$B$23,2,FALSE))
B34: timeframe | C34: 1 week | D34: 1 month | E34: 6 months | F34: 1 year | G34: 2 years | H34: 4 years | J34: 1wk | K34: 1mo | L34: 6mo | M34: 1yr | N34: 2yr | O34: 4yr | P34: Rating
B35: % | J35: =+IF(C35="","",VLOOKUP(C35,Sheet2!$F$10:$G$15,2,TRUE)) | K35: =+IF(D35="","",VLOOKUP(D35,Sheet2!$F$10:$G$15,2,TRUE)) | L35: =+IF(E35="","",VLOOKUP(E35,Sheet2!$F$18:$G$23,2,TRUE)) | M35: =+IF(F35="","",VLOOKUP(F35,Sheet2!$F$18:$G$23,2,TRUE)) | N35: =+IF(G35="","",VLOOKUP(G35,Sheet2!$F$26:$G$31,2,TRUE)) | O35: =+IF(H35="","",VLOOKUP(H35,Sheet2!$F$26:$G$31,2,TRUE)) | P35: =+IF(J35="","",0.05*J35+0.05*K35+0.15*L35+0.15*M35+0.3*N35+0.3*O35)
B36: Financial Balance
C39: Current | D39: 2025 | E39: =+D39-1 -> 2024 | F39: =+E39-1 -> 2023 | G39: =+F39-1 -> 2022 | H39: =+G39-1 -> 2021 | J39: Average | K39: Comment | P39: Rating
B40: Cash & Equivalents | K40: =+IF(D41="","",IF(D40<0,Sheet2!$C$27,VLOOKUP(D41,Sheet2!$A$27:$C$31,3,TRUE))) | P40: =+IF(K40="","",VLOOKUP(K40,Sheet2!$C$27:$D$31,2,FALSE))
B41: % change | D41: =+IF(OR(E40="",D40="",),"",(D40-E40)/E40) | E41: =+IF(OR(F40="",E40="",),"",(E40-F40)/F40) | F41: =+IF(OR(G40="",F40="",),"",(F40-G40)/G40) | G41: =+IF(OR(H40="",G40="",),"",(G40-H40)/H40) | J41: =+IF(D41="","",AVERAGE(D41:G41)) | K41: =+IF(J41="","",IF(AND(D40<0,E40<0),Sheet2!$C$35,VLOOKUP(J41,Sheet2!$A$35:$C$39,3,TRUE))) | P41: =+IF(K41="","",VLOOKUP(K41,Sheet2!$C$35:$D$39,2,FALSE))
C43: Current | D43: =+D39 -> 2025 | E43: =+E39 -> 2024 | F43: =+F39 -> 2023 | G43: =+G39 -> 2022 | H43: =+H39 -> 2021 | J43: Average | K43: Comment | P43: Rating
B44: Inventory | K44: =+IF(D45="","",IF(D44<0,Sheet2!$C$27,VLOOKUP(D45,Sheet2!$A$27:$C$31,3,TRUE))) | P44: =+IF(K44="","",VLOOKUP(K44,Sheet2!$C$27:$D$31,2,FALSE))
B45: % change | D45: =+IF(OR(E44="",D44="",),"",(D44-E44)/E44) | E45: =+IF(OR(F44="",E44="",),"",(E44-F44)/F44) | F45: =+IF(OR(G44="",F44="",),"",(F44-G44)/G44) | G45: =+IF(OR(H44="",G44="",),"",(G44-H44)/H44) | J45: =+IF(D45="","",AVERAGE(D45:G45)) | K45: =+IF(J45="","",IF(AND(D44<0,E44<0),Sheet2!$C$35,VLOOKUP(J45,Sheet2!$A$35:$C$39,3,TRUE))) | P45: =+IF(K45="","",VLOOKUP(K45,Sheet2!$C$35:$D$39,2,FALSE))
C47: Current | D47: =+D39 -> 2025 | E47: =+E39 -> 2024 | F47: =+F39 -> 2023 | G47: =+G39 -> 2022 | H47: =+H39 -> 2021 | J47: Average
B48: Total Current Assets
B49: % change | D49: =+IF(OR(E48="",D48="",),"",(D48-E48)/E48) | E49: =+IF(OR(F48="",E48="",),"",(E48-F48)/F48) | F49: =+IF(OR(G48="",F48="",),"",(F48-G48)/G48) | G49: =+IF(OR(H48="",G48="",),"",(G48-H48)/H48) | J49: =+IF(D49="","",AVERAGE(D49:G49))
C51: Current | D51: =+D39 -> 2025 | E51: =+E39 -> 2024 | F51: =+F39 -> 2023 | G51: =+G39 -> 2022 | H51: =+H39 -> 2021 | J51: Average
B52: Total Current Liabilities
B53: % change | D53: =+IF(OR(E52="",D52="",),"",(D52-E52)/E52) | E53: =+IF(OR(F52="",E52="",),"",(E52-F52)/F52) | F53: =+IF(OR(G52="",F52="",),"",(F52-G52)/G52) | G53: =+IF(OR(H52="",G52="",),"",(G52-H52)/H52) | J53: =+IF(D53="","",AVERAGE(D53:G53))
C55: Current | D55: =+D39 -> 2025 | E55: =+E39 -> 2024 | F55: =+F39 -> 2023 | G55: =+G39 -> 2022 | H55: =+H39 -> 2021 | J55: Average
B56: Property, Plant & Equipment
B57: % change | D57: =+IF(OR(E56="",D56="",),"",(D56-E56)/E56) | E57: =+IF(OR(F56="",E56="",),"",(E56-F56)/F56) | F57: =+IF(OR(G56="",F56="",),"",(F56-G56)/G56) | G57: =+IF(OR(H56="",G56="",),"",(G56-H56)/H56) | J57: =+IF(D57="","",AVERAGE(D57:G57))
C59: Current | D59: =+D39 -> 2025 | E59: =+E39 -> 2024 | F59: =+F39 -> 2023 | G59: =+G39 -> 2022 | H59: =+H39 -> 2021 | J59: Average | K59: Comment | P59: Rating
B60: Revenue | K60: =+IF(D61="","",IF(D60<0,Sheet2!$C$27,VLOOKUP(D61,Sheet2!$A$27:$C$31,3,TRUE))) | P60: =+IF(K60="","",VLOOKUP(K60,Sheet2!$C$27:$D$31,2,FALSE))
B61: % change | D61: =+IF(OR(E60="",D60="",),"",(D60-E60)/E60) | E61: =+IF(OR(F60="",E60="",),"",(E60-F60)/F60) | F61: =+IF(OR(G60="",F60="",),"",(F60-G60)/G60) | G61: =+IF(OR(H60="",G60="",),"",(G60-H60)/H60) | J61: =+IF(D61="","",AVERAGE(D61:G61)) | K61: =+IF(J61="","",IF(AND(D60<0,E60<0),Sheet2!$C$35,VLOOKUP(J61,Sheet2!$A$35:$C$39,3,TRUE))) | P61: =+IF(K61="","",VLOOKUP(K61,Sheet2!$C$35:$D$39,2,FALSE))
C63: Current | D63: =+D39 -> 2025 | E63: =+E39 -> 2024 | F63: =+F39 -> 2023 | G63: =+G39 -> 2022 | H63: =+H39 -> 2021 | J63: Average | K63: Comment | P63: Rating
B64: Net Income | K64: =+IF(D65="","",IF(D64<0,Sheet2!$C$27,VLOOKUP(D65,Sheet2!$A$27:$C$31,3,TRUE))) | P64: =+IF(K64="","",VLOOKUP(K64,Sheet2!$C$27:$D$31,2,FALSE))
B65: % change | D65: =+IF(OR(E64="",D64="",),"",(D64-E64)/E64) | E65: =+IF(OR(F64="",E64="",),"",(E64-F64)/F64) | F65: =+IF(OR(G64="",F64="",),"",(F64-G64)/G64) | G65: =+IF(OR(H64="",G64="",),"",(G64-H64)/H64) | J65: =+IF(D65="","",AVERAGE(D65:G65)) | K65: =+IF(J65="","",IF(AND(D64<0,E64<0),Sheet2!$C$35,VLOOKUP(J65,Sheet2!$A$35:$C$39,3,TRUE))) | P65: =+IF(K65="","",VLOOKUP(K65,Sheet2!$C$35:$D$39,2,FALSE))
C67: Current | D67: =+D39 -> 2025 | E67: =+E39 -> 2024 | F67: =+F39 -> 2023 | G67: =+G39 -> 2022 | H67: =+H39 -> 2021 | J67: Average | K67: Comment | P67: Rating
B68: Total Assets | K68: =+IF(D69="","",IF(D68<0,Sheet2!$C$27,VLOOKUP(D69,Sheet2!$A$27:$C$31,3,TRUE))) | P68: =+IF(K68="","",VLOOKUP(K68,Sheet2!$C$27:$D$31,2,FALSE))
B69: % change | D69: =+IF(OR(E68="",D68="",),"",(D68-E68)/E68) | E69: =+IF(OR(F68="",E68="",),"",(E68-F68)/F68) | F69: =+IF(OR(G68="",F68="",),"",(F68-G68)/G68) | G69: =+IF(OR(H68="",G68="",),"",(G68-H68)/H68) | J69: =+IF(D69="","",AVERAGE(D69:G69)) | K69: =+IF(J69="","",IF(AND(D68<0,E68<0),Sheet2!$C$35,VLOOKUP(J69,Sheet2!$A$35:$C$39,3,TRUE))) | P69: =+IF(K69="","",VLOOKUP(K69,Sheet2!$C$35:$D$39,2,FALSE))
C71: Current | D71: =+D39 -> 2025 | E71: =+E39 -> 2024 | F71: =+F39 -> 2023 | G71: =+G39 -> 2022 | H71: =+H39 -> 2021 | J71: Average
B72: Long-Term Debt
B73: / income | D73: =+IF(D64="","",D72/D64) | E73: =+IF(E64="","",E72/E64) | F73: =+IF(F64="","",F72/F64) | G73: =+IF(G64="","",G72/G64) | H73: =+IF(H64="","",H72/H64) | J73: =+IF(D73="","",AVERAGE(D73:G73))
C75: Current | D75: =+D39 -> 2025 | E75: =+E39 -> 2024 | F75: =+F39 -> 2023 | G75: =+G39 -> 2022 | H75: =+H39 -> 2021 | J75: Average
B76: Total Liabilities
B77: % change | D77: =+IF(OR(E76="",D76="",),"",(D76-E76)/E76) | E77: =+IF(OR(F76="",E76="",),"",(E76-F76)/F76) | F77: =+IF(OR(G76="",F76="",),"",(F76-G76)/G76) | G77: =+IF(OR(H76="",G76="",),"",(G76-H76)/H76) | J77: =+IF(D77="","",AVERAGE(D77:G77))
C79: Current | D79: =+D39 -> 2025 | E79: =+E39 -> 2024 | F79: =+F39 -> 2023 | G79: =+G39 -> 2022 | H79: =+H39 -> 2021 | J79: Average | K79: Comment | P79: Rating
B80: Shareholders' Equity | K80: =+IF(D81="","",IF(D80<0,Sheet2!$C$27,VLOOKUP(D81,Sheet2!$A$27:$C$31,3,TRUE))) | P80: =+IF(K80="","",VLOOKUP(K80,Sheet2!$C$27:$D$31,2,FALSE))
B81: % change | D81: =+IF(OR(E80="",D80="",),"",(D80-E80)/E80) | E81: =+IF(OR(F80="",E80="",),"",(E80-F80)/F80) | F81: =+IF(OR(G80="",F80="",),"",(F80-G80)/G80) | G81: =+IF(OR(H80="",G80="",),"",(G80-H80)/H80) | J81: =+IF(D81="","",AVERAGE(D81:G81)) | K81: =+IF(J81="","",IF(AND(D80<0,E80<0),Sheet2!$C$35,VLOOKUP(J81,Sheet2!$A$35:$C$39,3,TRUE))) | P81: =+IF(K81="","",VLOOKUP(K81,Sheet2!$C$35:$D$39,2,FALSE))
C83: Current | D83: =+D39 -> 2025 | E83: =+E39 -> 2024 | F83: =+F39 -> 2023 | G83: =+G39 -> 2022 | H83: =+H39 -> 2021 | J83: Average | K83: Comment | P83: Rating
B84: Treasury Stock | K84: =+IF(D85="","",VLOOKUP(D85,Sheet2!$A$42:$C$43,3,TRUE)) | P84: =+IF(K84="","",VLOOKUP(K84,Sheet2!$C$42:$D$43,2,FALSE))
B85: - > Share-Adjusted Debt to Shareholders | D85: =+IF(D76="","",D76/(D80-2*D84)) | E85: =+IF(E76="","",E76/(E80-2*E84)) | F85: =+IF(F76="","",F76/(F80-2*F84)) | G85: =+IF(G76="","",G76/(G80-2*G84)) | H85: =+IF(H76="","",H76/(H80-2*H84)) | J85: =+IF(D85="","",AVERAGE(D85:G85)) | K85: =+IF(J85="","",VLOOKUP(J85,Sheet2!$A$45:$C$46,3,TRUE)) | P85: =+IF(K85="","",VLOOKUP(K85,Sheet2!$C$45:$D$46,2,FALSE))
B86: % change | D86: =+IF(OR(E85="",D85="",),"",(D85-E85)/E85) | E86: =+IF(OR(F85="",E85="",),"",(E85-F85)/F85) | F86: =+IF(OR(G85="",F85="",),"",(F85-G85)/G85) | G86: =+IF(OR(H85="",G85="",),"",(G85-H85)/H85) | J86: =+IF(D86="","",AVERAGE(D86:G86))
C88: Current | D88: =+D39 -> 2025 | E88: =+E39 -> 2024 | F88: =+F39 -> 2023 | G88: =+G39 -> 2022 | H88: =+H39 -> 2021 | J88: Average | K88: Comment | P88: Rating
B89: Retained Earnings
B90: Yearly Net Earnings | D90: =+IF(D89="","",D89-E89) | E90: =+IF(E89="","",E89-F89) | F90: =+IF(F89="","",F89-G89) | G90: =+IF(G89="","",G89-H89) | K90: =+IF(D91="","",IF(D89<0,Sheet2!$C$50,VLOOKUP(D91,Sheet2!A50:C54,3,TRUE))) | P90: =+IF(K90="","",VLOOKUP(K90,Sheet2!$C$50:$D$54,2,FALSE))
B91: % change | D91: =+IF(D90="","",D90/E89) | E91: =+IF(E90="","",E90/F89) | F91: =+IF(F90="","",F90/G89) | G91: =+IF(G90="","",G90/H89) | J91: =+IF(D91="","",AVERAGE(D91:G91)) | K91: =+IF(J91="","",IF(AND(C89<0,D89<0),Sheet2!$C$56,VLOOKUP(J91,Sheet2!$A$56:$C$60,3,TRUE))) | P91: =+IF(K91="","",VLOOKUP(K91,Sheet2!$C$56:$D$60,2,FALSE))
C93: Current | D93: =+D39 -> 2025 | E93: =+E39 -> 2024 | F93: =+F39 -> 2023 | G93: =+G39 -> 2022 | H93: =+H39 -> 2021 | J93: Average | K93: Comment | P93: Rating
B94: Gross Profit | K94: =+IF(D95="","",IF(D94<0,Sheet2!$C$64,VLOOKUP(D95,Sheet2!$A$64:$C$68,3,TRUE))) | P94: =+IF(K94="","",VLOOKUP(K94,Sheet2!$C$64:$D$68,2,FALSE))
B95: % revenue | D95: =+IF(D94="","",D94/D60) | E95: =+IF(E94="","",E94/E60) | F95: =+IF(F94="","",F94/F60) | G95: =+IF(G94="","",G94/G60) | J95: =+IF(D95="","",AVERAGE(D95:G95)) | K95: =+IF(J95="","",IF(AND(C94<0,D94<0),Sheet2!$C$70,VLOOKUP(J95,Sheet2!$A$70:$C$74,3,TRUE))) | P95: =+IF(K95="","",VLOOKUP(K95,Sheet2!$C$70:$D$74,2,FALSE))
C97: Current | D97: =+D39 -> 2025 | E97: =+E39 -> 2024 | F97: =+F39 -> 2023 | G97: =+G39 -> 2022 | H97: =+H39 -> 2021 | J97: Average | K97: Comment | P97: Rating
B98: Profit Margin | K98: =+IF(D99="","",IF(D98<0,Sheet2!$C$78,VLOOKUP(D99,Sheet2!$A$78:$C$82,3,TRUE))) | P98: =+IF(K98="","",VLOOKUP(K98,Sheet2!$C$78:$D$82,2,FALSE))
B99: % change | D99: =+IF(OR(E98="",D98="",),"",(D98-E98)/E98) | E99: =+IF(OR(F98="",E98="",),"",(E98-F98)/F98) | F99: =+IF(OR(G98="",F98="",),"",(F98-G98)/G98) | G99: =+IF(OR(H98="",G98="",),"",(G98-H98)/H98) | J99: =+IF(D99="","",AVERAGE(D99:G99)) | K99: =+IF(J99="","",IF(AND(E98<0,D98<0),Sheet2!$C$84,VLOOKUP(J99,Sheet2!$A$84:$C$88,3,TRUE))) | P99: =+IF(K99="","",VLOOKUP(K99,Sheet2!$C$84:$D$88,2,FALSE))
C101: Current | D101: =+D39 -> 2025 | E101: =+E39 -> 2024 | F101: =+F39 -> 2023 | G101: =+G39 -> 2022 | H101: =+H39 -> 2021 | J101: Average | K101: Comment | P101: Rating
B102: Selling, General & Admin | K102: =+IF(D103="","",VLOOKUP(D103,Sheet2!$A$92:$C$94,3,TRUE)) | P102: =+IF(D103="","",VLOOKUP(D103,Sheet2!$A$92:$C$94,2,TRUE))
B103: % gross profit | D103: =+IF(D102="","",D102/D94) | E103: =+IF(E102="","",E102/E94) | F103: =+IF(F102="","",F102/F94) | G103: =+IF(G102="","",G102/G94) | J103: =+IF(D103="","",AVERAGE(D103:G103)) | K103: =+IF(J103="","",VLOOKUP(J103,Sheet2!$A$96:$C$98,3,TRUE)) | P103: =+IF(J103="","",VLOOKUP(J103,Sheet2!$A$96:$C$98,2,TRUE))
C105: Current | D105: =+D39 -> 2025 | E105: =+E39 -> 2024 | F105: =+F39 -> 2023 | G105: =+G39 -> 2022 | H105: =+H39 -> 2021 | J105: Average | K105: Comment | P105: Rating
B106: Operating Income
B107: Interest Expense | K107: =+IF(D108="","",IF(D106<0,Sheet2!$C$104,VLOOKUP(D108,Sheet2!$A$102:$C$104,3,TRUE))) | P107: =+IF(K107="","",VLOOKUP(K107,Sheet2!$C$102:$D$107,2,FALSE))
B108: % operating income | D108: =+IF(D107="","",D107*(-1)/D106) | E108: =+IF(E107="","",E107*(-1)/E106) | F108: =+IF(F107="","",F107*(-1)/F106) | G108: =+IF(G107="","",G107*(-1)/G106) | H108: =+IF(H107="","",H107*(-1)/H106) | J108: =+IF(D108="","",AVERAGE(D108:G108)) | K108: =+IF(J108="","",IF(AND(D106<0,E106<0),Sheet2!$C$107,VLOOKUP(J108,Sheet2!$A$105:$C$107,3,TRUE))) | P108: =+IF(K108="","",VLOOKUP(K108,Sheet2!$C$102:$D$107,2,FALSE))
B110: Cashflow
C112: Current | D112: =+D39 -> 2025 | E112: =+E39 -> 2024 | F112: =+F39 -> 2023 | G112: =+G39 -> 2022 | H112: =+H39 -> 2021 | J112: Average | K112: Comment | P112: Rating
B113: Capital Expenditures | J113: =+IF(D113="","",SUM(D113:H113)) | K113: =+IF(D114="","",IF(D113<0,Sheet2!$C$113,VLOOKUP(D114,Sheet2!$A$110:$C$113,3,TRUE))) | P113: =+IF(K113="","",VLOOKUP(K113,Sheet2!$C$110:$D$117,2,FALSE))
B114: /income | D114: =+IF(D113="","",D113*(-1)/D64) | E114: =+IF(E113="","",E113*(-1)/E64) | F114: =+IF(F113="","",F113*(-1)/F64) | G114: =+IF(G113="","",G113*(-1)/G64) | H114: =+IF(H113="","",H113*(-1)/H64) | K114: =+IF(J114="","",IF(AND(D113<0,E113<0),Sheet2!$C$117,VLOOKUP(J114,Sheet2!$A$114:$C$117,3,TRUE))) | P114: =+IF(K114="","",VLOOKUP(K114,Sheet2!$C$110:$D$117,2,FALSE))
C116: Current | D116: =+D39 -> 2025 | E116: =+E39 -> 2024 | F116: =+F39 -> 2023 | G116: =+G39 -> 2022 | H116: =+H39 -> 2021 | J116: Average | K116: Comment | P116: Rating
B117: Operating Cash Flow | K117: =+IF(D118="","",IF(D117<0,Sheet2!$C$27,VLOOKUP(D118,Sheet2!$A$27:$C$31,3,TRUE))) | P117: =+IF(K117="","",VLOOKUP(K117,Sheet2!$C$27:$D$31,2,FALSE))
B118: %growth | D118: =+IF(OR(E117="",D117="",),"",(D117-E117)/E117) | E118: =+IF(OR(F117="",E117="",),"",(E117-F117)/F117) | F118: =+IF(OR(G117="",F117="",),"",(F117-G117)/G117) | G118: =+IF(OR(H117="",G117="",),"",(G117-H117)/H117) | J118: =+IF(D118="","",AVERAGE(D118:G118)) | K118: =+IF(J118="","",IF(AND(D117<0,E117<0),Sheet2!$C$35,VLOOKUP(J118,Sheet2!$A$35:$C$39,3,TRUE))) | P118: =+IF(K118="","",VLOOKUP(K118,Sheet2!$C$35:$D$39,2,FALSE))
C120: Current | D120: =+D39 -> 2025 | E120: =+E39 -> 2024 | F120: =+F39 -> 2023 | G120: =+G39 -> 2022 | H120: =+H39 -> 2021 | J120: Average | K120: Comment | P120: Rating
B121: Free Cash Flow | K121: =+IF(D122="","",IF(D121<0,Sheet2!$C$27,VLOOKUP(D122,Sheet2!$A$27:$C$31,3,TRUE))) | P121: =+IF(K121="","",VLOOKUP(K121,Sheet2!$C$27:$D$31,2,FALSE))
B122: %growth | D122: =+IF(OR(E121="",D121="",),"",(D121-E121)/E121) | E122: =+IF(OR(F121="",E121="",),"",(E121-F121)/F121) | F122: =+IF(OR(G121="",F121="",),"",(F121-G121)/G121) | G122: =+IF(OR(H121="",G121="",),"",(G121-H121)/H121) | J122: =+IF(D122="","",AVERAGE(D122:G122)) | K122: =+IF(J122="","",IF(AND(D121<0,E121<0),Sheet2!$C$35,VLOOKUP(J122,Sheet2!$A$35:$C$39,3,TRUE))) | P122: =+IF(K122="","",VLOOKUP(K122,Sheet2!$C$35:$D$39,2,FALSE))
C124: Current | D124: =+D39 -> 2025 | E124: =+E39 -> 2024 | F124: =+F39 -> 2023 | G124: =+G39 -> 2022 | H124: =+H39 -> 2021 | J124: Average | K124: Comment | P124: Rating
B125: Issuance of Common Stock
B126: Repurchase of Common Stock | K126: =+IF(D127="","",IF(D127<0,"Company rebought its stocks in the last year.","Company didn't rebought its stocks in the last year.")) | P126: =+IF(D127="","",IF(D127<0,5,1))
B127: Net Issuance of stock | D127: =+IF(AND(D125="",D126=""),"",D125+D126) | E127: =+IF(AND(E125="",E126=""),"",E125+E126) | F127: =+IF(AND(F125="",F126=""),"",F125+F126) | G127: =+IF(AND(G125="",G126=""),"",G125+G126) | H127: =+IF(AND(H125="",H126=""),"",H125+H126) | J127: =+IF(D127="","",AVERAGE(D127:H127)) | K127: =+IF(J127="","",IF(J127<0,"Company usually rebuy its stocks","Company usually don't rebuy its stocks")) | P127: =+IF(J127="","",IF(J127<0,5,1))
B130: Ratios
...

Sheet Sheet2
A1: Recommendation | B1: Rating | E1: Rating | F1: 1 | G1: 5
A2: strong_buy | B2: 5 | F2: min | G2: max
A3: buy | B3: 4
A4: hold | B4: 3
A5: sell | B5: 1
A6: strong_sell | B6: 0
A7: none | B7: 0
A8: Volatility | B8: Rating | F8: Stock
A9: Low volatility | B9: 5 | F9: Short-term
A10: Normal volatility | B10: 3 | F10: -1 | G10: 0
A11: High volatility | B11: 0 | F11: -0.03 | G11: 1
F12: -0.01 | G12: 2
A13: Risk | B13: Rating | F13: 0.01 | G13: 3
A14: 1 | B14: 5 | F14: 0.03 | G14: 4
A15: 2 | B15: 5 | F15: 0.05 | G15: 5
A16: 3 | B16: 4
A17: 4 | B17: 4 | F17: Medium-term
A18: 5 | B18: 3 | F18: -1 | G18: 0
A19: 6 | B19: 3 | F19: 0 | G19: 1
A20: 7 | B20: 2 | F20: 0.02 | G20: 2
A21: 8 | B21: 2 | F21: 0.06 | G21: 3
A22: 9 | B22: 1 | F22: 0.1 | G22: 4
A23: 10 | B23: 0 | F23: 0.15 | G23: 5
F25: long-term
A26: Recent Performance | F26: -1 | G26: 0
A27: -100000000000 | B27: 1 | C27: Last year's growth was mediocre or negative. | D27: 0 | F27: 0.05 | G27: 1
A28: 0.025 | B28: 2 | C28: Last year's growth was low. | D28: =+B28 -> 2 | F28: 0.1 | G28: 2
A29: 0.05 | B29: 3 | C29: Last year's growth was moderately positive. | D29: =+B29 -> 3 | F29: 0.15 | G29: 3
A30: 0.1 | B30: 4 | C30: Last year's growth was very positive. | D30: =+B30 -> 4 | F30: 0.25 | G30: 4
A31: 0.15 | B31: 5 | C31: Last year's growth was outstanding. | D31: =+B31 -> 5 | F31: 0.3 | G31: 5
A33: Overall Performance
A35: -100000000000 | B35: 1 | C35: Overall growth was mediocre or negative. | D35: 0
A36: 0.025 | B36: 2 | C36: Overall growth was low. | D36: =+B36 -> 2
A37: 0.05 | B37: 3 | C37: Overall growth was moderately positive. | D37: =+B37 -> 3
A38: 0.1 | B38: 4 | C38: Overall growth was very positive. | D38: =+B38 -> 4
A39: 0.15 | B39: 5 | C39: Overall growth was outstanding. | D39: =+B39 -> 5
A41: - > Share-Adjusted Debt to Shareholders
A42: 0 | B42: 5 | C42: Adjusted debt in relation to patrimony. | D42: =+B42 -> 5
A43: 0.8 | B43: 1 | C43: Disadjusted debt in relation to patrimony. | D43: 0
A45: 0 | B45: 5 | C45: On average, adjusted debt in relation to patrimony. | D45: =+B45 -> 5
A46: 0.8 | B46: 1 | C46: On average, Disadjusted debt in relation to patrimony. | D46: 0
A49: Yearly Net Earnings
A50: -100000000000 | B50: 1 | C50: Innexistent earning's growth. | D50: 0
A51: 0.03 | B51: 2 | C51: Low earning's growth. | D51: =+B51 -> 2
A52: 0.05 | B52: 3 | C52: Normal earning's growth. | D52: =+B52 -> 3
A53: 0.07 | B53: 4 | C53: Good earning's growth. | D53: =+B53 -> 4
A54: 0.08 | B54: 5 | C54: Optimal earning's growth. | D54: =+B54 -> 5
A56: -100000000000 | B56: 1 | C56: Innexistent earning's growth in the last years. | D56: 0
A57: 0.03 | B57: 2 | C57: Low earning's growth in the last years. | D57: =+B57 -> 2
A58: 0.05 | B58: 3 | C58: Normal earning's growth in the last years. | D58: =+B58 -> 3
A59: 0.07 | B59: 4 | C59: Good earning's growth in the last years. | D59: =+B59 -> 4
A60: 0.08 | B60: 5 | C60: Optimal earning's growth in the last years. | D60: =+B60 -> 5
A63: Gross Profit
A64: -100000000000 | B64: 1 | C64: Mediocre profit. | D64: 0
A65: 0.1 | B65: 2 | C65: Very low profit. | D65: =+B65 -> 2
A66: 0.2 | B66: 3 | C66: Low profit. | D66: =+B66 -> 3
A67: 0.3 | B67: 4 | C67: Normal profit. | D67: =+B67 -> 4
A68: 0.4 | B68: 5 | C68: Good profit. | D68: =+B68 -> 5
A70: -100000000000 | B70: 1 | C70: Mediocre profit in the last years. | D70: 0
A71: 0.1 | B71: 2 | C71: Very low profit in the last years. | D71: =+B71 -> 2
A72: 0.2 | B72: 3 | C72: Low profit in the last years. | D72: =+B72 -> 3
A73: 0.3 | B73: 4 | C73: Normal profit in the last years. | D73: =+B73 -> 4
A74: 0.4 | B74: 5 | C74: Good profit in the last years. | D74: =+B74 -> 5
A77: Profit Margin
A78: -100000000000 | B78: 1 | C78: Profit margin's growth not relevant. | D78: 0
A79: 0.025 | B79: 2 | C79: Low growth of the profit margin. | D79: =+B79 -> 2
A80: 0.05 | B80: 3 | C80: Normal growth of the profit margin. | D80: =+B80 -> 3
A81: 0.1 | B81: 4 | C81: Good growth of the profit margin. | D81: =+B81 -> 4
A82: 0.2 | B82: 5 | C82: Optimal growth of the profit margin. | D82: =+B82 -> 5
A84: -100000000000 | B84: 1 | C84: Profit margin's growth not relevant in the last years. | D84: 0
A85: 0.025 | B85: 2 | C85: Low growth of the profit margin in the last years. | D85: =+B85 -> 2
A86: 0.05 | B86: 3 | C86: Normal growth of the profit margin in the last years. | D86: =+B86 -> 3
A87: 0.1 | B87: 4 | C87: Good growth of the profit margin in the last years. | D87: =+B87 -> 4
A88: 0.2 | B88: 5 | C88: Optimal growth of the profit margin in the last years. | D88: =+B88 -> 5
A91: Selling, General & Admin
A92: -100000000000 | B92: 5 | C92: SGA costs well controlled. | D92: =+B92 -> 5
A93: 0.3 | B93: 3 | C93: SGA costs are controlled but can be lower. | D93: =+B93 -> 3
A94: 0.39 | B94: 1 | C94: SGA costs are out of control. | D94: 0
A96: -100000000000 | B96: 5 | C96: SGA costs well controlled in the last years. | D96: =+B96 -> 5
A97: 0.3 | B97: 3 | C97: In the last years SGA costs have been controlled but can be lower. | D97: =+B97 -> 3
A98: 0.39 | B98: 1 | C98: In the last years SGA costs have been out of control. | D98: 0
A101: Interest Expense
A102: -100000000000 | B102: 5 | C102: Optimal interest income. | D102: =+B102 -> 5
A103: 0.15 | B103: 5 | C103: Optimal interest income. | D103: =+B103 -> 5
A104: 0.2 | B104: 1 | C104: Bad interest income. | D104: 0
A105: 0 | B105: 5 | C105: Optimal interest income over the years. | D105: =+B105 -> 5
A106: 0.15 | B106: 5 | C106: Optimal interest income over the years. | D106: =+B106 -> 5
A107: 0.2 | B107: 1 | C107: Bad interest income over the years. | D107: 0
A109: Capital Expenditures
A110: -100000000000 | B110: 5 | C110: Expenditures are totally under control. | D110: =+B110 -> 5
A111: 0.25 | B111: 5 | C111: Expenditures are totally under control. | D111: =+B111 -> 5
A112: 0.5 | B112: 3 | C112: Expenditures under control. | D112: =+B112 -> 3
A113: 0.55 | B113: 1 | C113: Expenditures out of control. | D113: 0
A114: 0 | B114: 5 | C114: Expenditures always under control. | D114: =+B114 -> 5
A115: 0.25 | B115: 5 | C115: Expenditures always under control. | D115: =+B115 -> 5
A116: 0.5 | B116: 3 | C116: Expenditures usually under control. | D116: =+B116 -> 3
A117: 0.55 | B117: 1 | C117: Expenditures usually out of control. | D117: 0
A120: EPS (Basic)
A121: -100000000000 | B121: 1 | C121: Mediocre earnings or loss per share in the last year. | D121: 0
A122: 0.005 | B122: 2 | C122: Low earnings per share in the last year. | D122: =+B122 -> 2
...
